amusement/__init__.py
amusement/attraction.py
amusement/park.py
amusement/ride.py
amusement/show.py
amusement-0.1.dist-info/DESCRIPTION.rst
amusement-0.1.dist-info/METADATA
amusement-0.1.dist-info/RECORD
amusement-0.1.dist-info/WHEEL
amusement-0.1.dist-info/entry_points.txt
amusement-0.1.dist-info/metadata.json
amusement-0.1.dist-info/top_level.txt
