Metadata-Version: 2.0
Name: amusement
Version: 0.1
Summary: A python package and CLI to get wait times for rides at various theme parks
Home-page: http://github.com/astephen2/amusement
Author: Alex Stephen
Author-email: UNKNOWN
License: MIT
Platform: UNKNOWN
Requires-Dist: Click
Requires-Dist: beautifulsoup4
Requires-Dist: nose
Requires-Dist: python-dateutil
Requires-Dist: requests
